README.md
setup.py
underline/__init__.py
underline.egg-info/PKG-INFO
underline.egg-info/SOURCES.txt
underline.egg-info/dependency_links.txt
underline.egg-info/requires.txt
underline.egg-info/top_level.txt
underline/core/__init__.py
underline/core/selector.py
underline/utils/__init__.py
underline/utils/colors.py